pykit/__init__.py
pykit/config.py
pykit/exceptions.py
pykit/protobuf_format.py
pykit/cache/__init__.py
pykit/cache/redis.py
pykit/circuitbreaker/__init__.py
pykit/client/__init__.py
pykit/client/rabbit_mq.py
pykit/cmd/__init__.py
pykit/cmd/grpc.py
pykit/cmd/subscribe.py
pykit/database/__init__.py
pykit/database/api.py
pykit/database/exceptions.py
pykit/database/transaction.py
pykit/database/orm/__init__.py
pykit/database/orm/session.py
pykit/database/orm/sqlalchemy.py
pykit/ddd/__init__.py
pykit/ddd/framework.py
pykit/ddd/transaction.py
pykit/ddd/utils.py
pykit/error/__init__.py
pykit/error/code_pb2.py
pykit/error/error_pb2.py
pykit/error/error_reason_pb2.py
pykit/event/__init__.py
pykit/event/publisher.py
pykit/event/subscriber.py
pykit/event/rabbitmq/__init__.py
pykit/log/__init__.py
pykit/thridpatry/__init__.py
pykit/transport/__init__.py
pykit/transport/grpc.py
qlkit-0.0.27.dist-info/LICENSE
qlkit-0.0.27.dist-info/METADATA
qlkit-0.0.27.dist-info/WHEEL
qlkit-0.0.27.dist-info/top_level.txt
qlkit-0.0.27.dist-info/RECORD
